Metadata-Version: 2.1
Name: bedrock-tools
Version: 0.2.1
Summary: A small Python library that simplifies Amazon Bedrock Converse API function calling (i.e., tool use).
Home-page: https://github.com/jritsema/bedrock-tools
Author: John Ritsema
Author-email: john_ritsema@yahoo.com
Keywords: ai genai bedrock tools function-calling
Classifier: Programming Language :: Python :: 3
Classifier: License :: OSI Approved :: MIT License
Classifier: Operating System :: OS Independent
Requires-Python: >=3.11
